hepsylex/Constants.py
hepsylex/Lexicons.py
hepsylex/LexiconsAPI.py
hepsylex/__init__.py
hepsylex/Resources/__init__.py
hepsylex/Resources/For documentation purposes/__init__.py
hepsylex/Resources/For documentation purposes/Topic Modeling 2020/__init__.py
hepsylex/Resources/For documentation purposes/Topic Modeling 2020/from_topics_to_lexicons.py
hepsylex-1.0.4.dist-info/LICENSE
hepsylex-1.0.4.dist-info/METADATA
hepsylex-1.0.4.dist-info/WHEEL
hepsylex-1.0.4.dist-info/top_level.txt
hepsylex-1.0.4.dist-info/RECORD
