Metadata-Version: 2.1
Name: hepsylex
Version: 1.0.4
Summary: Hebrew Psychological Lexicons
Home-page: https://github.com/natalieshapira/HebrewPsychologicalLexicons
Author: Natalie Shapira
Author-email: nd1234@gmail.com
License: UNKNOWN
Project-URL: Bug Tracker, https://github.com/natalieshapira/HebrewPsychologicalLexicons/issues
Platform: UNKNOWN
Classifier: Programming Language :: Python :: 3
Classifier: License :: OSI Approved :: Apache Software License
Classifier: Operating System :: OS Independent
Requires-Python: >=3.6
License-File: LICENSE
